LICENSE
MANIFEST.in
README.rst
buildout.cfg
develop.cfg
pyproject.toml
requirements.txt
setup.py
version.txt
bob/__init__.py
bob.db.atnt.egg-info/PKG-INFO
bob.db.atnt.egg-info/SOURCES.txt
bob.db.atnt.egg-info/dependency_links.txt
bob.db.atnt.egg-info/entry_points.txt
bob.db.atnt.egg-info/not-zip-safe
bob.db.atnt.egg-info/requires.txt
bob.db.atnt.egg-info/top_level.txt
bob/db/__init__.py
bob/db/atnt/__init__.py
bob/db/atnt/driver.py
bob/db/atnt/models.py
bob/db/atnt/query.py
bob/db/atnt/test.py
doc/conf.py
doc/guide.rst
doc/index.rst
doc/py_api.rst